helpu/__init__.py
helpu/helpu.py
helpu-0.0.102.dist-info/LICENSE.txt
helpu-0.0.102.dist-info/METADATA
helpu-0.0.102.dist-info/WHEEL
helpu-0.0.102.dist-info/top_level.txt
helpu-0.0.102.dist-info/RECORD
